PiCalc/__init__.py
PiCalc-0.1.dist-info/METADATA
PiCalc-0.1.dist-info/WHEEL
PiCalc-0.1.dist-info/top_level.txt
PiCalc-0.1.dist-info/RECORD
