Metadata-Version: 2.1
Name: PiCalc
Version: 0.1
Summary: This is code which will find value of pi
Home-page: UNKNOWN
Author: Dhaval
Author-email: UNKNOWN
License: UNKNOWN
Platform: UNKNOWN
